{
  "sections": [
    {
      "phases": [
        {"type": "prolog", "duration": "10s", "name": "Prolog", "icon": "🚀", "text": "Prepare to focus", "message": "Get ready!", "color": "#00CED1"}
      ],
      "repeat": 1
    },
    {
      "phases": [
        {"type": "work", "duration": "25m", "name": "Work", "icon": "🧠", "text": "Stay focused", "message": "Focus time!", "color": "#00FF00"},
        {"type": "rest", "duration": "5m", "name": "Rest", "icon": "💤", "text": "Take a break", "message": "Break time!", "color": "#87CEEB"}
      ],
      "repeat": 4
    },
    {
      "phases": [
        {"type": "longRest", "duration": "30m", "name": "Long Rest", "icon": "😴", "text": "Great work! Long break", "message": "Good job! Take a break", "color": "#DDA0DD"}
      ],
      "repeat": 1
    }
  ],
  "repeat": 3
}
